diskarray/__init__.py
diskarray/command.py
diskarray/diskarray.py
diskarray/exception.py
diskarray/strarray.py
diskarray/vararray.py
diskarray-0.1.9.dist-info/LICENSE
diskarray-0.1.9.dist-info/METADATA
diskarray-0.1.9.dist-info/WHEEL
diskarray-0.1.9.dist-info/entry_points.txt
diskarray-0.1.9.dist-info/top_level.txt
diskarray-0.1.9.dist-info/RECORD
